xfyunsdkcore/__init__.py
xfyunsdkcore/http_client.py
xfyunsdkcore/signature.py
xfyunsdkcore/utils.py
xfyunsdkcore/errors/__init__.py
xfyunsdkcore/log/__init__.py
xfyunsdkcore/log/logger.py
xfyunsdkcore/model/__init__.py
xfyunsdkcore/model/ai_ppt_model.py
xfyunsdkcore/model/aiui_knowledge_model.py
xfyunsdkcore/model/lfasr_model.py
xfyunsdkcore/model/voice_clone_model.py
xfyunsdkcore-0.0.3.dist-info/LICENSE
xfyunsdkcore-0.0.3.dist-info/METADATA
xfyunsdkcore-0.0.3.dist-info/WHEEL
xfyunsdkcore-0.0.3.dist-info/top_level.txt
xfyunsdkcore-0.0.3.dist-info/RECORD
