Metadata-Version: 2.1
Name: xfyunsdkcore
Version: 0.0.3
Summary: a sdk core for xfyun
Author: zyding6
Author-email: zyding6@iflytek.com
Requires-Python: >=3.7.1
License-File: LICENSE
Requires-Dist: httpx
Requires-Dist: websocket-client <2.0.0
